tests/__init__.py
tests/test_dataset.py
tests/test_histogram.py
tests/test_overload.py
torchic/__init__.py
torchic/core/__init__.py
torchic/core/analysis_flow.py
torchic/core/api.py
torchic/core/dataset.py
torchic/core/fit.py
torchic/core/fitter.py
torchic/core/graph.py
torchic/core/histogram.py
torchic/core/plotter.py
torchic/core/roofitter.py
torchic/core/RooCustomPdfs/RooGausExp.cxx
torchic/core/RooCustomPdfs/RooGausExp.hh
torchic/physics/BetheBloch.hh
torchic/physics/ITS.py
torchic/physics/__init__.py
torchic/physics/calibration.py
torchic/physics/simulations/ExponentialDecaySimulation.cpp
torchic/physics/simulations/ExponentialDecaySimulation.cxx
torchic/physics/simulations/TwoBodyDecaySimulation.cpp
torchic/physics/simulations/TwoBodyDecaySimulation.cxx
torchic/physics/simulations/__init__.py
torchic/physics/simulations/test.cxx
torchic/physics/simulations/wrappers.py
torchic/roopdf/__init__.py
torchic/roopdf/RooCustomPdfs/RooGausDExp.hh
torchic/roopdf/RooCustomPdfs/RooGausExp.cxx
torchic/roopdf/RooCustomPdfs/RooGausExp.hh
torchic/roopdf/RooCustomPdfs/RooSillPdf.hh
torchic/utils/__init__.py
torchic/utils/overload.py
torchic/utils/root.py
torchic/utils/terminal_colors.py
torchic/utils/timeit.py
torchic-0.5.39.dist-info/licenses/LICENSE
torchic-0.5.39.dist-info/METADATA
torchic-0.5.39.dist-info/WHEEL
torchic-0.5.39.dist-info/top_level.txt
torchic-0.5.39.dist-info/RECORD
