Metadata-Version: 2.4
Name: torchic
Version: 0.5.39
Summary: A Python library for data analysis in python and ROOT (tailored for high energy physics)
Home-page: https://github.com/GiorgioAlbertoLucia/torchic
Author: Giorgio Alberto Lucia, Roberta Ferioli
Author-email: giogioalberto@gmail.com
Classifier: Programming Language :: Python :: 3
Classifier: License :: OSI Approved :: MIT License
Classifier: Operating System :: OS Independent
Requires-Python: >=3.6
License-File: LICENSE
Requires-Dist: numpy<2.0
Requires-Dist: pandas
Requires-Dist: scikit-learn
Requires-Dist: pyYAML
Requires-Dist: uproot
Provides-Extra: root
Requires-Dist: ROOT; extra == "root"
Dynamic: author
Dynamic: author-email
Dynamic: classifier
Dynamic: description
Dynamic: description-content-type
Dynamic: home-page
Dynamic: license-file
Dynamic: provides-extra
Dynamic: requires-dist
Dynamic: requires-python
Dynamic: summary
